myVTKPythonLibrary/__init__.py
myVTKPythonLibrary/addDeformationGradients.py
myVTKPythonLibrary/addEquivDeviatoricStrainsFromDeformationGradients.py
myVTKPythonLibrary/addImageGradient.py
myVTKPythonLibrary/addImageHessian.py
myVTKPythonLibrary/addJacobiansFromDeformationGradients.py
myVTKPythonLibrary/addMappingFromPointsToCells.py
myVTKPythonLibrary/addMappingToCellData.py
myVTKPythonLibrary/addMappingToPointData.py
myVTKPythonLibrary/addPDataNormals.py
myVTKPythonLibrary/addPhysicalGroupToMesh.py
myVTKPythonLibrary/addPrincipalDirections.py
myVTKPythonLibrary/addStrainsFromDeformationGradients.py
myVTKPythonLibrary/addStrainsFromDisplacements.py
myVTKPythonLibrary/addVertices.py
myVTKPythonLibrary/array_algebra.py
myVTKPythonLibrary/createArray.py
myVTKPythonLibrary/createCharArray.py
myVTKPythonLibrary/createDoubleArray.py
myVTKPythonLibrary/createFloatArray.py
myVTKPythonLibrary/createImage.py
myVTKPythonLibrary/createIntArray.py
myVTKPythonLibrary/createLongArray.py
myVTKPythonLibrary/createShortArray.py
myVTKPythonLibrary/createUnsignedCharArray.py
myVTKPythonLibrary/createUnsignedIntArray.py
myVTKPythonLibrary/createUnsignedLongArray.py
myVTKPythonLibrary/createUnsignedShortArray.py
myVTKPythonLibrary/fast_array_algebra.py
myVTKPythonLibrary/getCellCenters.py
myVTKPythonLibrary/getCellLocator.py
myVTKPythonLibrary/getClippedPDataUsingField.py
myVTKPythonLibrary/getClippedPDataUsingPlane.py
myVTKPythonLibrary/getImageDimensionality.py
myVTKPythonLibrary/getImageDimensions.py
myVTKPythonLibrary/getImageInterpolator.py
myVTKPythonLibrary/getMaskFromMesh.py
myVTKPythonLibrary/getMaskedImageUsingMesh.py
myVTKPythonLibrary/getMassProperties.py
myVTKPythonLibrary/getMeshVolume.py
myVTKPythonLibrary/getOverlapCardinalities.py
myVTKPythonLibrary/getPDataSurfaceArea.py
myVTKPythonLibrary/getPointLocator.py
myVTKPythonLibrary/getPointsInCell.py
myVTKPythonLibrary/getThresholdedPData.py
myVTKPythonLibrary/getThresholdedUGrid.py
myVTKPythonLibrary/getVoxels.py
myvtkpythonlibrary-2025.4.18.dist-info/licenses/LICENSE
myvtkpythonlibrary-2025.4.18.dist-info/METADATA
myvtkpythonlibrary-2025.4.18.dist-info/WHEEL
myvtkpythonlibrary-2025.4.18.dist-info/top_level.txt
myvtkpythonlibrary-2025.4.18.dist-info/RECORD
